instapyper/__init__.py
instapyper/async_client.py
instapyper/cli.py
instapyper/client.py
instapyper/exceptions.py
instapyper/models.py
instapyper/py.typed
instapyper-0.0.3.dist-info/METADATA
instapyper-0.0.3.dist-info/WHEEL
instapyper-0.0.3.dist-info/entry_points.txt
instapyper-0.0.3.dist-info/RECORD
