Metadata-Version: 2.4
Name: instapyper
Version: 0.0.3
Summary: Modern Python wrapper for the Instapaper Full API
Author-email: Barabazs <31799121+Barabazs@users.noreply.github.com>
License-Expression: MIT
Keywords: api,bookmarks,instapaper,read-later
Classifier: Development Status :: 4 - Beta
Classifier: Intended Audience :: Developers
Classifier: License :: OSI Approved :: MIT License
Classifier: Programming Language :: Python :: 3
Classifier: Programming Language :: Python :: 3.10
Classifier: Programming Language :: Python :: 3.11
Classifier: Programming Language :: Python :: 3.12
Classifier: Programming Language :: Python :: 3.13
Classifier: Programming Language :: Python :: 3.14
Classifier: Typing :: Typed
Requires-Python: >=3.10
Requires-Dist: authlib>=1.2
Requires-Dist: httpx>=0.25
Requires-Dist: requests-oauthlib>=1.3
Requires-Dist: requests>=2.28
Requires-Dist: typing-extensions>=4.0
Provides-Extra: all
Requires-Dist: keyring>=25.0; extra == 'all'
Requires-Dist: rich>=13.0; extra == 'all'
Requires-Dist: typer>=0.9; extra == 'all'
Provides-Extra: cli
Requires-Dist: rich>=13.0; extra == 'cli'
Requires-Dist: typer>=0.9; extra == 'cli'
Provides-Extra: keyring
Requires-Dist: keyring>=25.0; extra == 'keyring'
